<states><state id="0" start="true"><rules><rule><input>0</input><result>1</result></rule><rule><input>1</input><result>1</result></rule><rule><input>2</input><result>1</result></rule><rule><input>3</input><result>1</result></rule><rule><input>4</input><result>1</result></rule><rule><input>5</input><result>1</result></rule><rule><input>6</input><result>1</result></rule><rule><input>+</input><result>1</result></rule><rule><input>-</input><result>1</result></rule></rules></state><state id="1"><rules><rule><input>0</input><result>1</result></rule><rule><input>1</input><result>1</result></rule><rule><input>2</input><result>1</result></rule><rule><input>3</input><result>1</result></rule><rule><input>4</input><result>1</result></rule><rule><input>5</input><result>1</result></rule><rule><input>6</input><result>1</result></rule><rule><input>.</input><result>2</result></rule></rules></state><state id="2"><rules><rule><input>0</input><result>2</result></rule><rule><input>1</input><result>2</result></rule><rule><input>2</input><result>2</result></rule><rule><input>3</input><result>2</result></rule><rule><input>4</input><result>2</result></rule><rule><input>5</input><result>2</result></rule><rule><input>6</input><result>2</result></rule></rules></state></states>